README.rst
ls_json.py
setup.cfg
setup.py
ls_json.egg-info/.pydio_id
ls_json.egg-info/PKG-INFO
ls_json.egg-info/SOURCES.txt
ls_json.egg-info/dependency_links.txt
ls_json.egg-info/entry_points.txt
ls_json.egg-info/top_level.txt