Metadata-Version: 1.0
Name: ls-json
Version: 1.0
Summary: ls_json traverses either the provided path or current dir and returns the file tree (with file sizes) in json format
Home-page: https://github.com/andrewleech/ls_json
Author: Andrew Leech
Author-email: andrew@alelec.net
License: PSF
Keywords: directory tree json
Platform: UNKNOWN
